[
  {
    "full_name": "open-sauced/api.opensauced.pizza",
    "stargazers_count": 17,
    "open_issues_count": 20,
    "forks_count": 7
  },
  {
    "full_name": "open-sauced/hot",
    "stargazers_count": 223,
    "open_issues_count": 41,
    "forks_count": 79
  },
  {
    "full_name": "httpie/httpie",
    "stargazers_count": 26391,
    "open_issues_count": 134,
    "forks_count": 3753
  },
  {
    "full_name": "brob/plug11ty.com",
    "stargazers_count": 12,
    "open_issues_count": 14,
    "forks_count": 21
  },
  {
    "full_name": "prometheus/prometheus",
    "stargazers_count": 46706,
    "open_issues_count": 863,
    "forks_count": 7867
  },
  {
    "full_name": "actions/typescript-action",
    "stargazers_count": 1331,
    "open_issues_count": 48,
    "forks_count": 348
  },
  {
    "full_name": "nickytonline/epic-actions",
    "stargazers_count": 3,
    "open_issues_count": 2,
    "forks_count": 0
  },
  {
    "full_name": "open-sauced/actions",
    "stargazers_count": 7,
    "open_issues_count": 5,
    "forks_count": 10
  },
  {
    "full_name": "jasonericdavis/FF_Picker",
    "stargazers_count": 3,
    "open_issues_count": 7,
    "forks_count": 2
  },
  {
    "full_name": "all-contributors/all-contributors",
    "stargazers_count": 6858,
    "open_issues_count": 55,
    "forks_count": 1728
  },
  {
    "full_name": "all-contributors/app",
    "stargazers_count": 495,
    "open_issues_count": 38,
    "forks_count": 157
  },
  {
    "full_name": "nightscout/cgm-remote-monitor",
    "stargazers_count": 2035,
    "open_issues_count": 189,
    "forks_count": 68386
  },
  {
    "full_name": "Team-TAU/tau",
    "stargazers_count": 137,
    "open_issues_count": 27,
    "forks_count": 35
  }
]