[
  {
    "full_name": "pa11y/pa11y",
    "stargazers_count": 3479,
    "open_issues_count": 46,
    "forks_count": 243
  },
  {
    "full_name": "open-sauced/contributor.info",
    "stargazers_count": 4,
    "open_issues_count": 4,
    "forks_count": 1
  },
  {
    "full_name": "cbh123/charl-e",
    "stargazers_count": 370,
    "open_issues_count": 11,
    "forks_count": 16
  },
  {
    "full_name": "testing-library/playwright-testing-library",
    "stargazers_count": 211,
    "open_issues_count": 17,
    "forks_count": 7
  },
  {
    "full_name": "dequelabs/axe-core-npm",
    "stargazers_count": 411,
    "open_issues_count": 46,
    "forks_count": 36
  },
  {
    "full_name": "open-sauced/api.opensauced.pizza",
    "stargazers_count": 7,
    "open_issues_count": 21,
    "forks_count": 4
  },
  {
    "full_name": "cocogitto/cocogitto",
    "stargazers_count": 233,
    "open_issues_count": 28,
    "forks_count": 28
  },
  {
    "full_name": "chadstewart/you-go-backend-project",
    "stargazers_count": 4,
    "open_issues_count": 0,
    "forks_count": 0
  },
  {
    "full_name": "KonomiAI/Chronicle",
    "stargazers_count": 6,
    "open_issues_count": 25,
    "forks_count": 1
  },
  {
    "full_name": "terminusdb/terminusdb",
    "stargazers_count": 2003,
    "open_issues_count": 140,
    "forks_count": 89
  },
  {
    "full_name": "mtfoley/pr-compliance-action",
    "stargazers_count": 136,
    "open_issues_count": 9,
    "forks_count": 9
  },
  {
    "full_name": "microsoft/playwright",
    "stargazers_count": 43335,
    "open_issues_count": 775,
    "forks_count": 2079
  },
  {
    "full_name": "open-sauced/hot",
    "stargazers_count": 173,
    "open_issues_count": 32,
    "forks_count": 68
  },
  {
    "full_name": "dequelabs/axe-core",
    "stargazers_count": 4796,
    "open_issues_count": 227,
    "forks_count": 673
  },
  {
    "full_name": "firecracker-microvm/firecracker",
    "stargazers_count": 19614,
    "open_issues_count": 133,
    "forks_count": 1412
  },
  {
    "full_name": "kefimochi/sync-contribution-graph",
    "stargazers_count": 194,
    "open_issues_count": 6,
    "forks_count": 11
  },
  {
    "full_name": "0-vortex/open-sauced-conventional-commit-test",
    "stargazers_count": 2,
    "open_issues_count": 0,
    "forks_count": 0
  },
  {
    "full_name": "prometheus/prometheus",
    "stargazers_count": 44782,
    "open_issues_count": 744,
    "forks_count": 7532
  },
  {
    "full_name": "nickytonline/epic-actions",
    "stargazers_count": 3,
    "open_issues_count": 2,
    "forks_count": 0
  },
  {
    "full_name": "aws/jsii",
    "stargazers_count": 2094,
    "open_issues_count": 245,
    "forks_count": 184
  },
  {
    "full_name": "vercel-community/php",
    "stargazers_count": 740,
    "open_issues_count": 24,
    "forks_count": 107
  },
  {
    "full_name": "actions/typescript-action",
    "stargazers_count": 1202,
    "open_issues_count": 40,
    "forks_count": 309
  },
  {
    "full_name": "netlify/netlify-cms",
    "stargazers_count": 15779,
    "open_issues_count": 777,
    "forks_count": 2837
  },
  {
    "full_name": "conventional-changelog/conventional-changelog",
    "stargazers_count": 6641,
    "open_issues_count": 245,
    "forks_count": 665
  },
  {
    "full_name": "open-sauced/actions",
    "stargazers_count": 6,
    "open_issues_count": 6,
    "forks_count": 10
  },
  {
    "full_name": "jasonericdavis/FF_Picker",
    "stargazers_count": 3,
    "open_issues_count": 7,
    "forks_count": 2
  },
  {
    "full_name": "chadstewart/tech-is-hiring-search-management-tool",
    "stargazers_count": 2,
    "open_issues_count": 0,
    "forks_count": 0
  },
  {
    "full_name": "FredKSchott/snowpack",
    "stargazers_count": 19762,
    "open_issues_count": 397,
    "forks_count": 988
  },
  {
    "full_name": "open-sauced/docs.opensauced.pizza",
    "stargazers_count": 17,
    "open_issues_count": 17,
    "forks_count": 18
  },
  {
    "full_name": "saulpw/visidata",
    "stargazers_count": 6038,
    "open_issues_count": 49,
    "forks_count": 222
  }
]